gitpush/__doc__.py
gitpush/__init__.py
gitpush/cli.py
gitpush_tool-0.3.6.dist-info/licenses/LICENSE
gitpush_tool-0.3.6.dist-info/METADATA
gitpush_tool-0.3.6.dist-info/WHEEL
gitpush_tool-0.3.6.dist-info/entry_points.txt
gitpush_tool-0.3.6.dist-info/top_level.txt
gitpush_tool-0.3.6.dist-info/RECORD
